blogs/__init__.py
blogs/admin.py
blogs/apps.py
blogs/context.py
blogs/forms.py
blogs/models.py
blogs/test_models.py
blogs/test_views.py
blogs/urls.py
blogs/views.py
blogs/management/commands/file_cleanup.py
blogs/migrations/0001_initial.py
blogs/migrations/0002_delete_popular.py
blogs/migrations/0003_auto_20240614_1303.py
blogs/migrations/0004_auto_20240615_1044.py
blogs/migrations/0005_auto_20240615_1137.py
blogs/migrations/0006_auto_20240618_1317.py
blogs/migrations/0007_category_color.py
blogs/migrations/0008_advertisement_anchorlink.py
blogs/migrations/0009_auto_20251109_1137.py
blogs/migrations/0010_auto_20251111_1713.py
blogs/migrations/__init__.py
blogs/static/blogs/css/create-style.css
blogs/static/blogs/css/detail-style.css
blogs/static/blogs/css/index-style.css
blogs/static/blogs/css/markdown-style.css
blogs/static/blogs/css/nnfx-dark.css
blogs/static/blogs/image/blogs_img.png
blogs/static/blogs/image/glenn-carstens-peters-npxXWgQ33ZQ-unsplash.jpg
blogs/static/blogs/image/zyanya-bmo-kJTQrwWkQ2k-unsplash.jpg
blogs/static/blogs/js/highlight.js
blogs/static/blogs/js/languages/apache.js
blogs/static/blogs/js/languages/apache.min.js
blogs/static/blogs/js/languages/bash.js
blogs/static/blogs/js/languages/bash.min.js
blogs/static/blogs/js/languages/css.js
blogs/static/blogs/js/languages/css.min.js
blogs/static/blogs/js/languages/django.js
blogs/static/blogs/js/languages/django.min.js
blogs/static/blogs/js/languages/dockerfile.js
blogs/static/blogs/js/languages/dockerfile.min.js
blogs/static/blogs/js/languages/ini.js
blogs/static/blogs/js/languages/ini.min.js
blogs/static/blogs/js/languages/javascript.js
blogs/static/blogs/js/languages/javascript.min.js
blogs/static/blogs/js/languages/json.js
blogs/static/blogs/js/languages/json.min.js
blogs/static/blogs/js/languages/markdown.js
blogs/static/blogs/js/languages/markdown.min.js
blogs/static/blogs/js/languages/nginx.js
blogs/static/blogs/js/languages/nginx.min.js
blogs/static/blogs/js/languages/python-repl.js
zfl_blogs-2.2.3.dist-info/METADATA
zfl_blogs-2.2.3.dist-info/WHEEL
zfl_blogs-2.2.3.dist-info/licenses/LICENSE.txt
zfl_blogs-2.2.3.dist-info/RECORD
