Metadata-Version: 2.4
Name: zfl-blogs
Version: 2.2.3
Summary: blogs on zfl
Project-URL: Documentation, https://github.com/kenno-warise/zfl-blogs/blob/main/README.md
Project-URL: Issues, https://github.com/kenno-warise/zfl-blogs/issues
Project-URL: Source, https://github.com/kenno-warise/zfl-blogs
Author-email: You are name <example@gmail.com>
License-Expression: MIT
License-File: LICENSE.txt
Classifier: Development Status :: 4 - Beta
Classifier: Environment :: Web Environment
Classifier: Framework :: Django :: 2.2
Classifier: Intended Audience :: Developers
Classifier: Programming Language :: Python
Classifier: Programming Language :: Python :: 3.6
Classifier: Programming Language :: Python :: Implementation :: CPython
Classifier: Programming Language :: Python :: Implementation :: PyPy
Requires-Python: >=3.6
Requires-Dist: django-cleanup<=5.2.0
Requires-Dist: django-markdownx<=3.0.1
Requires-Dist: django<=2.2.28
